{
  "version": "0.3.14-fixed",
  "steps": [
    {
      "tag": "CreateSource",
      "source": "db"
    },
    {
      "tag": "CreateArgument",
      "location": {
        "tag": "Source",
        "source": "db"
      },
      "argument": "provider",
      "value": "\"sqlite\""
    },
    {
      "tag": "CreateArgument",
      "location": {
        "tag": "Source",
        "source": "db"
      },
      "argument": "url",
      "value": "\"file:../tmp/db.sqlite\""
    },
    {
      "tag": "CreateModel",
      "model": "Product"
    },
    {
      "tag": "CreateField",
      "model": "Product",
      "field": "id",
      "type": "Int",
      "arity": "Required"
    },
    {
      "tag": "CreateDirective",
      "location": {
        "path": {
          "tag": "Field",
          "model": "Product",
          "field": "id"
        },
        "directive": "id"
      }
    },
    {
      "tag": "CreateDirective",
      "location": {
        "path": {
          "tag": "Field",
          "model": "Product",
          "field": "id"
        },
        "directive": "default"
      }
    },
    {
      "tag": "CreateArgument",
      "location": {
        "tag": "Directive",
        "path": {
          "tag": "Field",
          "model": "Product",
          "field": "id"
        },
        "directive": "default"
      },
      "argument": "",
      "value": "autoincrement()"
    },
    {
      "tag": "CreateField",
      "model": "Product",
      "field": "name",
      "type": "String",
      "arity": "Optional"
    },
    {
      "tag": "CreateField",
      "model": "Product",
      "field": "description",
      "type": "String",
      "arity": "Optional"
    },
    {
      "tag": "CreateField",
      "model": "Product",
      "field": "price",
      "type": "Int",
      "arity": "Optional"
    }
  ]
}